{
  "MANUFACTURER": "Google",
  "MODEL": "Pixel 8 Pro",
  "FINGERPRINT": "google/husky/husky:14/AP4A.250205.004/12716org:user/release-keys",
  "BRAND": "google",
  "PRODUCT": "husky",
  "DEVICE": "husky",
  "RELEASE": "14",
  "ID": "AP4A.250205.004",
  "INCREMENTAL": "12716org",
  "TYPE": "user",
  "TAGS": "release-keys",
  "SECURITY_PATCH": "2025-02-05",
  "DEVICE_INITIAL_SDK_INT": "34",
  "BUILD_ID": "AP4A.250205.004",
  "VNDK_VERSION": "34",
  "*.build.display.id": "",
  "*.security_patch": "2025-02-05",
  "spoofBuild": true,
  "spoofProps": true,
  "spoofProvider": true,
  "spoofSignature": false,
  "verboseLogs": 0
}
